[
  {
    "id": "nfl-arizona-cardinals",
    "name": "Arizona Cardinals",
    "logoUrl": "https://a.espncdn.com/i/teamlogos/nfl/500-dark/ari.png",
    "answers": [
      "Cardinals"
    ]
  },
  {
    "id": "nfl-atlanta-falcons",
    "name": "Atlanta Falcons",
    "logoUrl": "https://a.espncdn.com/i/teamlogos/nfl/500-dark/atl.png",
    "answers": [
      "Falcons"
    ]
  },
  {
    "id": "nfl-baltimore-ravens",
    "name": "Baltimore Ravens",
    "logoUrl": "https://a.espncdn.com/i/teamlogos/nfl/500-dark/bal.png",
    "answers": [
      "Ravens"
    ]
  },
  {
    "id": "nfl-buffalo-bills",
    "name": "Buffalo Bills",
    "logoUrl": "https://a.espncdn.com/i/teamlogos/nfl/500-dark/buf.png",
    "answers": [
      "Bills"
    ]
  },
  {
    "id": "nfl-carolina-panthers",
    "name": "Carolina Panthers",
    "logoUrl": "https://a.espncdn.com/i/teamlogos/nfl/500-dark/car.png",
    "answers": [
      "Panthers"
    ]
  },
  {
    "id": "nfl-chicago-bears",
    "name": "Chicago Bears",
    "logoUrl": "https://a.espncdn.com/i/teamlogos/nfl/500-dark/chi.png",
    "answers": [
      "Bears"
    ]
  },
  {
    "id": "nfl-cincinnati-bengals",
    "name": "Cincinnati Bengals",
    "logoUrl": "https://a.espncdn.com/i/teamlogos/nfl/500-dark/cin.png",
    "answers": [
      "Bengals"
    ]
  },
  {
    "id": "nfl-cleveland-browns",
    "name": "Cleveland Browns",
    "logoUrl": "https://a.espncdn.com/i/teamlogos/nfl/500-dark/cle.png",
    "answers": [
      "Browns"
    ]
  },
  {
    "id": "nfl-dallas-cowboys",
    "name": "Dallas Cowboys",
    "logoUrl": "https://a.espncdn.com/i/teamlogos/nfl/500-dark/dal.png",
    "answers": [
      "Cowboys"
    ]
  },
  {
    "id": "nfl-denver-broncos",
    "name": "Denver Broncos",
    "logoUrl": "https://a.espncdn.com/i/teamlogos/nfl/500-dark/den.png",
    "answers": [
      "Broncos"
    ]
  },
  {
    "id": "nfl-detroit-lions",
    "name": "Detroit Lions",
    "logoUrl": "https://a.espncdn.com/i/teamlogos/nfl/500-dark/det.png",
    "answers": [
      "Lions"
    ]
  },
  {
    "id": "nfl-green-bay-packers",
    "name": "Green Bay Packers",
    "logoUrl": "https://a.espncdn.com/i/teamlogos/nfl/500-dark/gb.png",
    "answers": [
      "Packers"
    ]
  },
  {
    "id": "nfl-houston-texans",
    "name": "Houston Texans",
    "logoUrl": "https://a.espncdn.com/i/teamlogos/nfl/500-dark/hou.png",
    "answers": [
      "Texans"
    ]
  },
  {
    "id": "nfl-indianapolis-colts",
    "name": "Indianapolis Colts",
    "logoUrl": "https://a.espncdn.com/i/teamlogos/nfl/500-dark/ind.png",
    "answers": [
      "Colts"
    ]
  },
  {
    "id": "nfl-jacksonville-jaguars",
    "name": "Jacksonville Jaguars",
    "logoUrl": "https://a.espncdn.com/i/teamlogos/nfl/500-dark/jax.png",
    "answers": [
      "Jaguars",
      "Jags"
    ]
  },
  {
    "id": "nfl-kansas-city-chiefs",
    "name": "Kansas City Chiefs",
    "logoUrl": "https://a.espncdn.com/i/teamlogos/nfl/500-dark/kc.png",
    "answers": [
      "Chiefs",
      "KC Chiefs"
    ]
  },
  {
    "id": "nfl-las-vegas-raiders",
    "name": "Las Vegas Raiders",
    "logoUrl": "https://a.espncdn.com/i/teamlogos/nfl/500-dark/lv.png",
    "answers": [
      "Raiders"
    ]
  },
  {
    "id": "nfl-los-angeles-chargers",
    "name": "Los Angeles Chargers",
    "logoUrl": "https://a.espncdn.com/i/teamlogos/nfl/500-dark/lac.png",
    "answers": [
      "Chargers",
      "LA Chargers",
      "L.A. Chargers"
    ]
  },
  {
    "id": "nfl-los-angeles-rams",
    "name": "Los Angeles Rams",
    "logoUrl": "https://a.espncdn.com/i/teamlogos/nfl/500-dark/lar.png",
    "answers": [
      "Rams",
      "LA Rams",
      "L.A. Rams"
    ]
  },
  {
    "id": "nfl-miami-dolphins",
    "name": "Miami Dolphins",
    "logoUrl": "https://a.espncdn.com/i/teamlogos/nfl/500-dark/mia.png",
    "answers": [
      "Dolphins"
    ]
  },
  {
    "id": "nfl-minnesota-vikings",
    "name": "Minnesota Vikings",
    "logoUrl": "https://a.espncdn.com/i/teamlogos/nfl/500-dark/min.png",
    "answers": [
      "Vikings"
    ]
  },
  {
    "id": "nfl-new-england-patriots",
    "name": "New England Patriots",
    "logoUrl": "https://a.espncdn.com/i/teamlogos/nfl/500-dark/ne.png",
    "answers": [
      "Patriots",
      "Pats"
    ]
  },
  {
    "id": "nfl-new-orleans-saints",
    "name": "New Orleans Saints",
    "logoUrl": "https://a.espncdn.com/i/teamlogos/nfl/500-dark/no.png",
    "answers": [
      "Saints"
    ]
  },
  {
    "id": "nfl-new-york-giants",
    "name": "New York Giants",
    "logoUrl": "https://a.espncdn.com/i/teamlogos/nfl/500-dark/nyg.png",
    "answers": [
      "Giants"
    ]
  },
  {
    "id": "nfl-new-york-jets",
    "name": "New York Jets",
    "logoUrl": "https://a.espncdn.com/i/teamlogos/nfl/500-dark/nyj.png",
    "answers": [
      "Jets"
    ]
  },
  {
    "id": "nfl-philadelphia-eagles",
    "name": "Philadelphia Eagles",
    "logoUrl": "https://a.espncdn.com/i/teamlogos/nfl/500-dark/phi.png",
    "answers": [
      "Eagles"
    ]
  },
  {
    "id": "nfl-pittsburgh-steelers",
    "name": "Pittsburgh Steelers",
    "logoUrl": "https://a.espncdn.com/i/teamlogos/nfl/500-dark/pit.png",
    "answers": [
      "Steelers"
    ]
  },
  {
    "id": "nfl-san-francisco-49ers",
    "name": "San Francisco 49ers",
    "logoUrl": "https://a.espncdn.com/i/teamlogos/nfl/500-dark/sf.png",
    "answers": [
      "49ers",
      "Niners"
    ]
  },
  {
    "id": "nfl-seattle-seahawks",
    "name": "Seattle Seahawks",
    "logoUrl": "https://a.espncdn.com/i/teamlogos/nfl/500-dark/sea.png",
    "answers": [
      "Seahawks"
    ]
  },
  {
    "id": "nfl-tampa-bay-buccaneers",
    "name": "Tampa Bay Buccaneers",
    "logoUrl": "https://a.espncdn.com/i/teamlogos/nfl/500-dark/tb.png",
    "answers": [
      "Buccaneers",
      "Bucs"
    ]
  },
  {
    "id": "nfl-tennessee-titans",
    "name": "Tennessee Titans",
    "logoUrl": "https://a.espncdn.com/i/teamlogos/nfl/500-dark/ten.png",
    "answers": [
      "Titans"
    ]
  },
  {
    "id": "nfl-washington-commanders",
    "name": "Washington Commanders",
    "logoUrl": "https://a.espncdn.com/i/teamlogos/nfl/500-dark/wsh.png",
    "answers": [
      "Commanders"
    ]
  }
]